{"lines": {"header": {"cloc_url": "github.com/AlDanial/cloc", "cloc_version": "1.76", "elapsed_seconds": 1.13653016090393, "n_files": 75, "n_lines": 3562, "files_per_second": 65.990329671805, "lines_per_second": 3134.10072387959}, "TypeScript": {"nFiles": 39, "blank": 239, "comment": 76, "code": 1372}, "HTML": {"nFiles": 13, "blank": 58, "comment": 0, "code": 675}, "Python": {"nFiles": 5, "blank": 115, "comment": 44, "code": 464}, "JSON": {"nFiles": 9, "blank": 0, "comment": 0, "code": 404}, "JavaScript": {"nFiles": 2, "blank": 3, "comment": 4, "code": 52}, "Stylus": {"nFiles": 6, "blank": 4, "comment": 1, "code": 24}, "Markdown": {"nFiles": 1, "blank": 13, "comment": 0, "code": 14}, "SUM": {"blank": 432, "comment": 125, "code": 3005, "nFiles": 75}}}